tokenprice/__init__.py
tokenprice/commandline.py
tokenprice/core.py
tokenprice/currency.py
tokenprice/modeling.py
tokenprice/pricing.py
tokenprice/safeasyncio.py
tokenprice-0.1.1.dist-info/licenses/LICENSE
tokenprice-0.1.1.dist-info/METADATA
tokenprice-0.1.1.dist-info/WHEEL
tokenprice-0.1.1.dist-info/entry_points.txt
tokenprice-0.1.1.dist-info/top_level.txt
tokenprice-0.1.1.dist-info/RECORD
