Metadata-Version: 2.4
Name: tokenprice
Version: 0.1.1
Summary: API pricing estimates for 1k+ LLMs
Requires-Python: >=3.12
License-File: LICENSE
Requires-Dist: httpx>=0.28.1
Requires-Dist: pydantic>=2.12.5
Requires-Dist: async-lru>=2.0.4
Requires-Dist: click>=8.1.7
Dynamic: license-file
